sigmafolio/__init__.py
sigmafolio-0.1.0.dist-info/METADATA
sigmafolio-0.1.0.dist-info/WHEEL
sigmafolio-0.1.0.dist-info/RECORD
