Metadata-Version: 2.3
Name: sigmafolio
Version: 0.1.0
Summary: All your financial data in one place
Author: Ivan Georgiev
Author-email: ivan.georgiev@example.com
Requires-Python: >=3.10
Classifier: Programming Language :: Python :: 3
Classifier: Programming Language :: Python :: 3.10
Classifier: Programming Language :: Python :: 3.11
Classifier: Programming Language :: Python :: 3.12
Classifier: Programming Language :: Python :: 3.13
